main_pipe.v
// see notebook for full explanation

module pipe_mips32(clk1, clk2);
    input clk1, clk2; // two phase clock
    reg [31:0] pc, if_id_ir, if_id_npc;
    reg [31:0] id_ex_ir, id_ex_npc, id_ex_a, id_ex_b, id_ex_imm;
    reg [2:0] id_ex_type, ex_mem_type, mem_wb_type;
    reg [31:0] ex_mem_ir, ex_mem_aluout, ex_mem_b;
    reg ex_mem_cond;
    reg [31:0] mem_wb_ir, mem_wb_aluout, mem_wb_lmd;
    reg [31:0] Reg [0:31];
    reg [31:0] mem [0:1023];

    parameter add = 6'd0, sub = 6'd1, and_ = 6'd2, or_ = 6'd3, 
    slt = 6'd4, mul = 6'd5, hlt = 6'd63, lw = 6'd8, 
    sw = 6'd9, addi = 6'd10, subi = 6'd11, slti = 6'd12,
    bneqz = 6'd13, beqz = 6'd14;

    parameter rr_alu = 3'b000, rm_alu = 3'b001,
    load = 3'b010, store = 3'b011, branch = 3'b100,
    halt = 3'b101;
    // some "types" of instructions (for convenience
    // in determining what to do; these will be stored
    // in the "_type" registers)

    // rr-alu: register-register alu type
    // rm-alu: register-immediate alu type

    reg halted;
    reg taken_branch;

    // IF stage
    always @(posedge clk1)
        if (halted == 0)
            begin
                if (((ex_mem_ir[31:26] == beqz) && (ex_mem_cond == 1)) ||
                    ((ex_mem_ir[31:26] == bneqz) && (ex_mem_cond == 0)))
                    begin
                        if_id_ir <= #2 mem[ex_mem_aluout];
                        taken_branch <= #2 1'b1;
                        // taken_branch will be used in mem and wb
                        // stages
                        if_id_npc <= #2 ex_mem_aluout + 1;
                        pc <= #2 ex_mem_aluout + 1;
                    end
                else
                    begin
                        if_id_ir <= #2 mem[pc];
                        if_id_npc <= #2 pc + 1;
                        pc <= #2 pc + 1;
                    end
            end

    // ID
    always @(posedge clk2)
        if (halted == 0)
            begin
                // rs: check if rs is 0. if it is, 
                // assign 0 directly since 0 reg
                // only holds 0
                if (if_id_ir[25:21] == 5'b0)
                    id_ex_a <= 0;
                else
                    id_ex_a <= #2 Reg[if_id_ir[25:21]];

                // rt: same as with rs
                if (if_id_ir[20:16] == 5'b0)
                    id_ex_b <= 0;
                else
                    id_ex_b <= #2 Reg[if_id_ir[20:16]];

                id_ex_npc <= if_id_npc;
                id_ex_ir <= if_id_ir;
                id_ex_imm <= {{16{if_id_ir[15]}}, if_id_ir[15:0]};
                // sign extended
                case (if_id_ir[31:26])
                    add, sub, and_, or_, slt, mul: id_ex_type <= #2 rr_alu;
                    addi, subi, slti: id_ex_type <= #2 rm_alu;
                    lw: id_ex_type <= #2 load;
                    sw: id_ex_type <= #2 store;
                    bneqz, beqz: id_ex_type <= #2 branch;
                    hlt: id_ex_type <= #2 halt;
                    default: id_ex_type <= #2 halt; 
                    // invalid opcode => we should halt
                endcase

            end

    // EX
    always @(posedge clk1)
        if (halted == 0)
            begin
                ex_mem_type <= #2 id_ex_type;
                ex_mem_ir <= #2 id_ex_ir;
                taken_branch <= #2 0;
                // ### important! all instructions after the
                // 2 following a branch instruction should
                // be allowed to change state since pc has 
                // correctly been updated before they
                // were fetched

                case (id_ex_type)
                    rr_alu:
                        begin
                            case (id_ex_ir[31:26])
                                add: ex_mem_aluout <= #2 id_ex_a + id_ex_b;
                                sub: ex_mem_aluout <= #2 id_ex_a - id_ex_b;
                                and_: ex_mem_aluout <= #2 id_ex_a & id_ex_b;
                                or_: ex_mem_aluout <= #2 id_ex_a | id_ex_b;
                                slt: ex_mem_aluout <= #2 id_ex_a < id_ex_b;
                                mul: ex_mem_aluout <= #2 id_ex_a * id_ex_b;
                                default: ex_mem_aluout <= #2 32'hxxxxxxxx;
                            endcase
                        end
                    rm_alu:
                        begin
                            case (id_ex_ir[31:26])
                                addi: ex_mem_aluout <= #2 id_ex_a + id_ex_imm;
                                subi: ex_mem_aluout <= #2 id_ex_a - id_ex_imm;
                                slti: ex_mem_aluout <= #2 id_ex_a < id_ex_imm;
                                default: ex_mem_aluout <= #2 32'hxxxxxxxx;
                            endcase
                        end
                    load, store:
                        begin
                            ex_mem_aluout <= #2 id_ex_a + id_ex_imm;
                            ex_mem_b <= #2 id_ex_b;
                        end
                    branch:
                        begin
                            ex_mem_aluout <= #2 id_ex_npc + id_ex_imm;
                            ex_mem_cond <= #2 (id_ex_a == 0);
                        end
                endcase
            end

    // MEM

    always @(posedge clk2)
        if (halted == 0)
            begin
                mem_wb_type <= #2 ex_mem_type;
                mem_wb_ir <= #2 ex_mem_ir;

                case (ex_mem_type)
                    rr_alu, rm_alu:
                        mem_wb_aluout <= #2 ex_mem_aluout;
                    load:
                        mem_wb_lmd <= #2 mem[ex_mem_aluout];
                    store:
                        if (taken_branch == 0)
                        // taken_branch == 1 => disable write
                            mem[ex_mem_aluout] <= #2 ex_mem_b;
                endcase
            end

    // WB
    always @(posedge clk1)
        begin
            if (taken_branch == 0)
            // taken_branch == 1 => disable write
                case (mem_wb_type)
                    rr_alu: Reg[mem_wb_ir[15:11]] <= #2 mem_wb_aluout; // rd
                    rm_alu: Reg[mem_wb_ir[20:16]] <= #2 mem_wb_aluout; // rt
                    load: Reg[mem_wb_ir[20:16]] <= #2 mem_wb_lmd; // rt
                    halt: halted <= #2 1'b1;
                endcase
        end

endmodule

pipe_tb.v
/*
procedure for running programs on processor

1. load program from specific memory address
2. initialize pc with the starting address of the program
3. execution continues until hlt encountered
4. print results from memory to verify operation
*/

// example 1
/*
add three numbers 10, 20, 30 
as stored in processor registers

1. initialize register r1 with 10,
2. initialize r2 with 20
3. initialize r3 with 25
4. add the three numbers and store the partial sums
   in r4 and r5

program looks like

1. addi r1, r0, 10
(001010 00000 00001 0000000000001010)
2. addi r2, r0, 20
(001010 00000 00010 0000000000010100)
3. addi r3, r0, 25
(001010 00000 00011 0000000000011001)
4. add r4, r1, r2
(000000 00001 00010 00100 00000 000000)
5. add r5, r4, r3
(000000 00100 00011 00101 00000 000000)
6. hlt
(111111 00000 00000 00000 00000 000000)

note that since we are using two clocks, 
delaying hazards by one instruction is sufficient
between instructions 3 and 4 and two between 4 and 5
let the dummy instruction be 
or r7, r7, r7
(000011 00111 00111 0111100000000000)
*/

// // program 1

// module test_mips32;
//     reg clk1, clk2;

//     integer k1, k2;

//     pipe_mips32 mips(clk1, clk2);

//     initial begin
//         clk1 = 1'b0; clk2 = 1'b0;
//         repeat (20)
//             begin
//                 #5 clk1 = 1'b1; clk1 = 1'b0;
//                 #5 clk2 = 1'b1; clk2 = 1'b0;
//             end
//     end

//     initial begin
//         for (k1=0; k1 < 31; k1=k1+1)
//             begin
//                 mips.Reg[k1] = k1;
//             end

        
//         mips.mem[0] = 32'b00101000000000010000000000001010; //instr1
//         mips.mem[1] = 32'b00101000000000100000000000010100; //instr2
//         mips.mem[2] = 32'b00101000000000110000000000011001; //instr3
//         mips.mem[3] = 32'b00001100111001110111100000000000; //dummy
//         mips.mem[4] = 32'b00000000001000100010000000000000; //instr4
//         mips.mem[5] = 32'b00001100111001110111100000000000; //dummy
//         mips.mem[6] = 32'b00000000100000110010100000000000; //instr5
//         mips.mem[7] = 32'b11111100000000000000000000000000; //instr6
        
//         mips.halted = 0;
//         mips.pc = 0;
//         mips.taken_branch = 0;

//         #280 for (k2=0; k2 < 6; k2=k2+1)
//             begin
//                 $display("R%1d - %2d", k2, mips.Reg[k2]);
//             end

//     end

//     initial begin
//         $dumpfile ("mips.vcd");
//         $dumpvars (0, test_mips32);
//         #300 $finish;
//     end
// endmodule

// // program 2
// /*
// load a word stored in memory location 120, add 45 to
// it, and store the result in memory location 121

// 1. addi r1, r0, 120
// (001010 00000 00001 0000000001111000)
// 2. lw r2, 0(r1)
// (001000 00001 00010 0000000000000000)
// 3. addi r2, r2, 45
// (001010 00010 00010 0000000000101101)
// 4. sw r2, 1(r1)
// (001001 00010 00001 0000000000000001)
// 5. hlt
// (111111 00000 00000 00000 00000 000000)

// let the dummy be or r3, r3, r3
// */

// module test_mips32;
//     reg clk1, clk2;

//     integer k1;

//     pipe_mips32 mips(clk1, clk2);

//     initial begin
//         clk1 = 1'b0; clk2 = 1'b0;
//         repeat (50)
//             begin
//                 #5 clk1 = 1'b1; clk1 = 1'b0;
//                 #5 clk2 = 1'b1; clk2 = 1'b0;
//             end
//     end

//     initial begin
//         for (k1=0; k1 < 31; k1=k1+1)
//             begin
//                 mips.Reg[k1] = k1;
//             end

        
//         mips.mem[0] = 32'h28010078; //instr1
//         mips.mem[1] = 32'h0c631800; //dummy
//         mips.mem[2] = 32'h20220000; //instr2
//         mips.mem[3] = 32'h0c631800; //dummy
//         mips.mem[4] = 32'h2842002d; //instr3
//         mips.mem[5] = 32'h0c631800; //dummy
//         mips.mem[6] = 32'h24220001; //instr4
//         mips.mem[7] = 32'hfc000000; //instr5

//         mips.mem[120] = 85;
        
//         mips.halted = 0;
//         mips.pc = 0;
//         mips.taken_branch = 0;

//         #500 $display("mem[120]: %4d \nmem[121]: %4d", mips.mem[120], mips.mem[121]);

//     end

//     initial begin
//         $dumpfile ("mips2.vcd");
//         $dumpvars (0, test_mips32);
//         #600 $finish;
//     end
// endmodule

// program 3
/*
compute the factorial of a number n stored
in memory location 200 and store it in 198

addi r10, r0, 200
addi r2, r0, 1
lw r3, 0(r10)
loop: mul r2, r2, r3
      subi r3, r3, 1
      bneqz r3, loop
      // to get to loop, we need to add -3 to incremented
      // pc
      // (maybe -4 to accomodate for dummy instructions)
      // so we encode it as
      // 001101 00011 00000 1111111111111101
sw r2, -2(r10) // imm is 1111111111111110
hlt

let the dummy be or r20, r20, r20
*/

module test_mips32;
    reg clk1, clk2;

    integer k1;

    pipe_mips32 mips(clk1, clk2);

    initial begin
        clk1 = 1'b0; clk2 = 1'b0;
        repeat (50)
            begin
                #5 clk1 = 1'b1; clk1 = 1'b0;
                #5 clk2 = 1'b1; clk2 = 1'b0;
            end
    end

    initial begin
        for (k1=0; k1 < 31; k1=k1+1)
            begin
                mips.Reg[k1] = k1;
            end

        
        mips.mem[0] = 32'h280a00c8; //instr1
        mips.mem[1] = 32'h28020001; //instr2
        mips.mem[2] = 32'h0e94a000; //dummy
        mips.mem[3] = 32'h21430000; //instr3
        mips.mem[4] = 32'h0e94a000; //dummy
        mips.mem[5] = 32'h14431000; //instr4
        mips.mem[6] = 32'h2c630001; //instr5
        mips.mem[7] = 32'h0e94a000; //dummy
        mips.mem[8] = 32'h3460fffc; //instr6: bneqz with -4 offset
        mips.mem[9] = 32'h2542fffe; //instr7
        mips.mem[10] = 32'hfc000000; //instr8

        mips.mem[200] = 7; // find 7!
        
        mips.halted = 0;
        mips.pc = 0;
        mips.taken_branch = 0;

        #2000 $display("mem[200]: %2d \nmem[198]: %6d", mips.mem[200], mips.mem[198]);

    end

    initial begin
        $dumpfile ("mips3.vcd");
        $dumpvars (0, test_mips32);
        $monitor ("R2: %4d", mips.Reg[2]);
        #3000 $finish;
    end
endmodule

/*
-instruction set is turing complete
-until now we have only avoided control hazards
 by "taken_branch" and data hazards by inserting 
 dummy instructions this is typically done by 
 compilers (software)
-we have done it behaviourally, but for synthesis, 
 structural is preferred. then, the program will
 be generating the control signals for the pipelined
 datapath in a proper sequence
*/

mips2.vcd
$date
	Mon Jun 30 15:31:42 2025
$end
$version
	Icarus Verilog
$end
$timescale
	1s
$end
$scope module test_mips32 $end
$var reg 1 ! clk1 $end
$var reg 1 " clk2 $end
$var integer 32 # k1 [31:0] $end
$scope module mips $end
$var wire 1 ! clk1 $end
$var wire 1 " clk2 $end
$var parameter 6 $ add $end
$var parameter 6 % addi $end
$var parameter 6 & and_ $end
$var parameter 6 ' beqz $end
$var parameter 6 ( bneqz $end
$var parameter 3 ) branch $end
$var parameter 3 * halt $end
$var parameter 6 + hlt $end
$var parameter 3 , load $end
$var parameter 6 - lw $end
$var parameter 6 . mul $end
$var parameter 6 / or_ $end
$var parameter 3 0 rm_alu $end
$var parameter 3 1 rr_alu $end
$var parameter 6 2 slt $end
$var parameter 6 3 slti $end
$var parameter 3 4 store $end
$var parameter 6 5 sub $end
$var parameter 6 6 subi $end
$var parameter 6 7 sw $end
$var reg 32 8 ex_mem_aluout [31:0] $end
$var reg 32 9 ex_mem_b [31:0] $end
$var reg 1 : ex_mem_cond $end
$var reg 32 ; ex_mem_ir [31:0] $end
$var reg 3 < ex_mem_type [2:0] $end
$var reg 1 = halted $end
$var reg 32 > id_ex_a [31:0] $end
$var reg 32 ? id_ex_b [31:0] $end
$var reg 32 @ id_ex_imm [31:0] $end
$var reg 32 A id_ex_ir [31:0] $end
$var reg 32 B id_ex_npc [31:0] $end
$var reg 3 C id_ex_type [2:0] $end
$var reg 32 D if_id_ir [31:0] $end
$var reg 32 E if_id_npc [31:0] $end
$var reg 32 F mem_wb_aluout [31:0] $end
$var reg 32 G mem_wb_ir [31:0] $end
$var reg 32 H mem_wb_lmd [31:0] $end
$var reg 3 I mem_wb_type [2:0] $end
$var reg 32 J pc [31:0] $end
$var reg 1 K taken_branch $end
$upscope $end
$upscope $end
$enddefinitions $end
$comment Show the parameter values. $end
$dumpall
b1001 7
b1011 6
b1 5
b11 4
b1100 3
b100 2
b0 1
b1 0
b11 /
b101 .
b1000 -
b10 ,
b111111 +
b101 *
b100 )
b1101 (
b1110 '
b10 &
b1010 %
b0 $
$end
#0
$dumpvars
0K
b0 J
bx I
bx H
bx G
bx F
bx E
bx D
bx C
bx B
bx A
bx @
bx ?
bx >
0=
bx <
bx ;
x:
bx 9
bx 8
b11111 #
0"
0!
$end
#5
0!
#7
b1 J
b1 E
b101000000000010000000001111000 D
#10
b1111000 @
b101000000000010000000001111000 A
b1 B
b0 >
0"
#12
b1 C
b1 ?
#15
0!
#17
b1111000 8
b101000000000010000000001111000 ;
b1 <
b10 J
b10 E
b1100011000110001100000000000 D
#20
b1100000000000 @
b1100011000110001100000000000 A
b10 B
0"
#22
b1111000 F
b101000000000010000000001111000 G
b1 I
b0 C
b11 ?
b11 >
#25
0!
#27
b11 J
b11 E
b100000001000100000000000000000 D
b11 8
b1100011000110001100000000000 ;
b0 <
#30
b0 @
b100000001000100000000000000000 A
b11 B
0"
#32
b10 C
b10 ?
b1111000 >
b11 F
b1100011000110001100000000000 G
b0 I
#35
0!
#37
b10 9
b1111000 8
b100000001000100000000000000000 ;
b10 <
b100 J
b100 E
b1100011000110001100000000000 D
#40
b1100000000000 @
b1100011000110001100000000000 A
b100 B
0"
#42
b1010101 H
b100000001000100000000000000000 G
b10 I
b0 C
b11 ?
b11 >
#45
0!
#47
b101 J
b101 E
b101000010000100000000000101101 D
b11 8
b1100011000110001100000000000 ;
b0 <
#50
b101101 @
b101000010000100000000000101101 A
b101 B
0"
#52
b1 C
b1010101 ?
b1010101 >
b1100011000110001100000000000 G
b0 I
#55
0!
#57
b10000010 8
b101000010000100000000000101101 ;
b1 <
b110 J
b110 E
b1100011000110001100000000000 D
#60
b1100000000000 @
b1100011000110001100000000000 A
b110 B
0"
#62
b10000010 F
b101000010000100000000000101101 G
b1 I
b0 C
b11 ?
b11 >
#65
0!
#67
b111 J
b111 E
b100100001000100000000000000001 D
b11 8
b1100011000110001100000000000 ;
b0 <
#70
b1 @
b100100001000100000000000000001 A
b111 B
0"
#72
b11 C
b10000010 ?
b1111000 >
b11 F
b1100011000110001100000000000 G
b0 I
#75
0!
#77
b10000010 9
b1111001 8
b100100001000100000000000000001 ;
b11 <
b1000 J
b1000 E
b11111100000000000000000000000000 D
#80
b0 @
b11111100000000000000000000000000 A
b1000 B
b0 ?
b0 >
0"
#82
b100100001000100000000000000001 G
b11 I
b101 C
#85
0!
#87
b1001 J
b1001 E
bx D
b11111100000000000000000000000000 ;
b101 <
#90
bx @
bx A
b1001 B
0"
#92
bx ?
bx >
b11111100000000000000000000000000 G
b101 I
#95
0!
#97
1=
bx ;
b1010 J
b1010 E
